huekit/__init__.py
huekit/huekit.py
huekit-0.1.1.dist-info/METADATA
huekit-0.1.1.dist-info/WHEEL
huekit-0.1.1.dist-info/licenses/LICENSE.txt
huekit-0.1.1.dist-info/RECORD
