Metadata-Version: 2.1
Name: huekit
Version: 0.1.1
Summary: Enables ANSI escape code support for Windows 10 terminal. Has 8-bit ANSI color presets.
Author-email: AuraPy <zayanarshad@aurapy.co.uk>
License-File: LICENSE.txt
Classifier: License :: OSI Approved :: GNU General Public License v3 (GPLv3)
Classifier: Operating System :: OS Independent
Classifier: Programming Language :: Python :: 3
Requires-Python: >=3.9
